COPYING
COPYING.LESSER
LICENSE
MANIFEST.in
README.rst
requirements.txt
setup.cfg
setup.py
pytrr/__init__.py
pytrr/pytrr.py
pytrr/version.py
pytrr.egg-info/PKG-INFO
pytrr.egg-info/SOURCES.txt
pytrr.egg-info/dependency_links.txt
pytrr.egg-info/requires.txt
pytrr.egg-info/top_level.txt
test/test_pytrr.py