Metadata-Version: 1.1
Name: pytrr
Version: 0.4.1
Summary: A package for reading GROMACS .trr files
Home-page: https://github.com/andersle/pytrr
Author: Anders Lervik
Author-email: andersle@gmail.com
License: LGPLv2.1+
Keywords: gromacs simulation trr
Platform: UNKNOWN
Classifier: Development Status :: 3 - Alpha
Classifier: Environment :: Console
Classifier: Intended Audience :: Science/Research
Classifier: License :: OSI Approved :: GNU Lesser General Public License v2 or later (LGPLv2+)
Classifier: Natural Language :: English
Classifier: Operating System :: MacOS :: MacOS X
Classifier: Operating System :: POSIX
Classifier: Programming Language :: Python :: 3
Classifier: Programming Language :: Python :: 3.2
Classifier: Programming Language :: Python :: 3.3
Classifier: Programming Language :: Python :: 3.4
Classifier: Programming Language :: Python :: 3.5
Classifier: Topic :: Scientific/Engineering :: Physics
